README.md
setup.py
HuaServer/__init__.py
HuaServer.egg-info/PKG-INFO
HuaServer.egg-info/SOURCES.txt
HuaServer.egg-info/dependency_links.txt
HuaServer.egg-info/requires.txt
HuaServer.egg-info/top_level.txt
HuaServer/module/__init__.py
HuaServer/module/api.py
HuaServer/module/server.py