Metadata-Version: 2.1
Name: HuaServer
Version: 1.0.0
Summary: 张恒华的简约框架
Home-page: https://pypi.org/project/HuaServer/
Author: 张恒华
Author-email: 1652709417@qq.com
License: MIT Licence
Keywords: pip,Python,Hua,Web Server
Platform: any
Requires-Python: >=3.9
